enowshop_models/__init__.py
enowshop_models/base/__init__.py
enowshop_models/helpers/__init__.py
enowshop_models/helpers/helpers.py
enowshop_models/models/__init__.py
enowshop_models/models/category.py
enowshop_models/models/category_products.py
enowshop_models/models/employees.py
enowshop_models/models/employees_phones.py
enowshop_models/models/products.py
enowshop_models/models/promotion.py
enowshop_models/models/provide_phones.py
enowshop_models/models/provider.py
enowshop_models/models/provider_address.py
enowshop_models/models/users.py
enowshop_models/models/users_address.py
enowshop_models/models/users_password_code_recovery.py
enowshop_models/models/users_phones.py
enowshop_models-0.4.17.dist-info/LICENSE
enowshop_models-0.4.17.dist-info/METADATA
enowshop_models-0.4.17.dist-info/WHEEL
enowshop_models-0.4.17.dist-info/top_level.txt
enowshop_models-0.4.17.dist-info/RECORD
